xchainpy2_cosmos/__init__.py
xchainpy2_cosmos/const.py
xchainpy2_cosmos/cosm_client.py
xchainpy2_cosmos/models.py
xchainpy2_cosmos/utils.py
xchainpy2_cosmos/tests/test_cosm_client.py
xchainpy2_cosmos/tests/test_cosm_util.py
xchainpy2_cosmos/tests/test_models.py
xchainpy2_cosmos/tests/samples/40BD2FCF41252AD7EAEE313989DC9CB10A120CD384804DD0E9D87F1B388243BB.json
xchainpy2_cosmos-0.0.6.dist-info/LICENSE
xchainpy2_cosmos-0.0.6.dist-info/METADATA
xchainpy2_cosmos-0.0.6.dist-info/WHEEL
xchainpy2_cosmos-0.0.6.dist-info/top_level.txt
xchainpy2_cosmos-0.0.6.dist-info/RECORD
