Metadata-Version: 2.1
Name: xchainpy2_cosmos
Version: 0.0.6
Summary: XChainPy2 Cosmos Client
Author-email: Tirinox <developer@tirinox.ru>
License: MIT
Project-URL: source, https://github.com/tirinox/xchainpy
Keywords: Crypto,THORChain,Blockchain,XChain,Cosmos
Classifier: Development Status :: 3 - Alpha
Classifier: Intended Audience :: Developers
Classifier: Topic :: Software Development :: Build Tools
Classifier: License :: OSI Approved :: MIT License
Classifier: Programming Language :: Python :: 3
Classifier: Programming Language :: Python :: 3.6
Classifier: Programming Language :: Python :: 3.7
Classifier: Programming Language :: Python :: 3.8
Classifier: Programming Language :: Python :: 3.9
Classifier: Programming Language :: Python :: 3.10
Classifier: Programming Language :: Python :: 3.11
Requires-Python: >=3.7
License-File: LICENSE
Requires-Dist: bip-utils <3.0.0,>=2.7.0
Requires-Dist: pycryptodome <4.0,>=3.17
Requires-Dist: cosmpy >=0.9.1
Requires-Dist: aiohttp
Requires-Dist: xchainpy2-utils
Requires-Dist: xchainpy2-crypto
Requires-Dist: xchainpy2-client
Provides-Extra: test
Requires-Dist: pytest ; extra == 'test'
